{"t": "Subtitle 9 Parking for Disabled Persons and Helpers", "p": "/us/md/cities/baltimore/code/31/9", "et": "container", "dj": "/us/md/cities/baltimore/code/index.json", "fh": "/us/md/cities/baltimore/code/31/9/index.full.html", "sc": " Article 31, Subtitle 9", "sp": "library|City of Baltimore, Md., Code|31|9", "c": [{"t": "Part 1 Reserved Parking for Disabled Persons", "p": "/us/md/cities/baltimore/code/31/9/1", "et": "container", "sc": " Article 31, Subtitle 9, Part 1", "sp": "library|City of Baltimore, Md., Code|31|9|1", "c": [{"t": "\u00a7 9-1. Criteria for obtaining.", "p": "/us/md/cities/baltimore/code/31/9-1", "et": "section", "sc": " Article 31, \u00a7 9-1", "sp": "library|City of Baltimore, Md., Code|31|9|1|9-1", "c": [{"t": "(a)", "p": "/us/md/cities/baltimore/code/31/9-1#(a)", "et": "para", "sc": "Article 31, \u00a7 9-1(a)", "c": [{"t": "(1)", "p": "/us/md/cities/baltimore/code/31/9-1#(a)(1)", "et": "para", "sc": "Article 31, \u00a7 9-1(a)(1)", "x": "the disability of the applicant must be permanent or of a nature expected t"}, {"t": "(2)", "p": "/us/md/cities/baltimore/code/31/9-1#(a)(2)", "et": "para", "sc": "Article 31, \u00a7 9-1(a)(2)", "x": "the applicant must be unable to use public transportation, leaving a person"}, {"t": "(3)", "p": "/us/md/cities/baltimore/code/31/9-1#(a)(3)", "et": "para", "sc": "Article 31, \u00a7 9-1(a)(3)", "x": "the applicant must be the sole operator of the vehicle or, if the applicant"}, {"t": "(4)", "p": "/us/md/cities/baltimore/code/31/9-1#(a)(4)", "et": "para", "sc": "Article 31, \u00a7 9-1(a)(4)", "x": "parking space must be available that is not restricted by other parking reg"}, {"t": "(5)", "p": "/us/md/cities/baltimore/code/31/9-1#(a)(5)", "et": "para", "sc": "Article 31, \u00a7 9-1(a)(5)", "x": "off-street parking is not available, such as a driveway, garage, or parking"}, {"t": "(6)", "p": "/us/md/cities/baltimore/code/31/9-1#(a)(6)", "et": "para", "sc": "Article 31, \u00a7 9-1(a)(6)", "x": "the applicant submits an application in the form that the Director of Trans"}], "x": "In general."}, {"t": "(b)", "p": "/us/md/cities/baltimore/code/31/9-1#(b)", "et": "para", "sc": "Article 31, \u00a7 9-1(b)", "c": [{"t": "(1)", "p": "/us/md/cities/baltimore/code/31/9-1#(b)(1)", "et": "para", "sc": "Article 31, \u00a7 9-1(b)(1)", "c": [{"t": "(i)", "p": "/us/md/cities/baltimore/code/31/9-1#(b)(1)(i)", "et": "para", "sc": "Article 31, \u00a7 9-1(b)(1)(i)", "x": "a physician's statement, dated within the previous 6 months, describing the"}, {"t": "(ii)", "p": "/us/md/cities/baltimore/code/31/9-1#(b)(1)(ii)", "et": "para", "sc": "Article 31, \u00a7 9-1(b)(1)(ii)", "x": "signed statements approving the designation of reserved parking for the app"}], "x": "The application shall be accompanied by:"}, {"t": "(2)", "p": "/us/md/cities/baltimore/code/31/9-1#(b)(2)", "et": "para", "sc": "Article 31, \u00a7 9-1(b)(2)", "c": [{"t": "(i)", "p": "/us/md/cities/baltimore/code/31/9-1#(b)(2)(i)", "et": "para", "sc": "Article 31, \u00a7 9-1(b)(2)(i)", "x": "the Director determines that there are not enough properties in the block t"}, {"t": "(ii)", "p": "/us/md/cities/baltimore/code/31/9-1#(b)(2)(ii)", "et": "para", "sc": "Article 31, \u00a7 9-1(b)(2)(ii)", "x": "the Director, in consultation with the Director of the Community Relations "}], "x": "The Director may waive the requirements of paragraph (1)(ii) of this subsec"}], "x": "Required statements."}]}, {"t": "\u00a7 9-2. Procedure.", "p": "/us/md/cities/baltimore/code/31/9-2", "et": "section", "sc": " Article 31, \u00a7 9-2", "sp": "library|City of Baltimore, Md., Code|31|9|1|9-2", "c": [{"t": "(a)", "p": "/us/md/cities/baltimore/code/31/9-2#(a)", "et": "para", "sc": "Article 31, \u00a7 9-2(a)", "c": [{"t": "(1)", "p": "/us/md/cities/baltimore/code/31/9-2#(a)(1)", "et": "para", "sc": "Article 31, \u00a7 9-2(a)(1)", "x": "Any person desiring a reserved parking space and meeting the criteria of \u00a7 "}, {"t": "(2)", "p": "/us/md/cities/baltimore/code/31/9-2#(a)(2)", "et": "para", "sc": "Article 31, \u00a7 9-2(a)(2)", "x": "The Department shall review each application."}], "x": "Application to Department."}, {"t": "(b)", "p": "/us/md/cities/baltimore/code/31/9-2#(b)", "et": "para", "sc": "Article 31, \u00a7 9-2(b)", "c": [{"t": "(1)", "p": "/us/md/cities/baltimore/code/31/9-2#(b)(1)", "et": "para", "sc": "Article 31, \u00a7 9-2(b)(1)", "x": "a temporary permit shall be issued; and"}, {"t": "(2)", "p": "/us/md/cities/baltimore/code/31/9-2#(b)(2)", "et": "para", "sc": "Article 31, \u00a7 9-2(b)(2)", "x": "an administrative regulation describing the location of the reserved space "}], "x": "Approvals."}, {"t": "(c)", "p": "/us/md/cities/baltimore/code/31/9-2#(c)", "et": "para", "sc": "Article 31, \u00a7 9-2(c)", "c": [{"t": "(1)", "p": "/us/md/cities/baltimore/code/31/9-2#(c)(1)", "et": "para", "sc": "Article 31, \u00a7 9-2(c)(1)", "x": "If the Department determines that the applicant does not meet the criteria "}, {"t": "(2)", "p": "/us/md/cities/baltimore/code/31/9-2#(c)(2)", "et": "para", "sc": "Article 31, \u00a7 9-2(c)(2)", "x": "If the Department denies the permit, the applicant may appeal the decision "}], "x": "Denials."}]}, {"t": "\u00a7 9-3. Use, renewal, and termination.", "p": "/us/md/cities/baltimore/code/31/9-3", "et": "section", "sc": " Article 31, \u00a7 9-3", "sp": "library|City of Baltimore, Md., Code|31|9|1|9-3", "c": [{"t": "(a)", "p": "/us/md/cities/baltimore/code/31/9-3#(a)", "et": "para", "sc": "Article 31, \u00a7 9-3(a)", "x": "Permit to be displayed."}, {"t": "(b)", "p": "/us/md/cities/baltimore/code/31/9-3#(b)", "et": "para", "sc": "Article 31, \u00a7 9-3(b)", "c": [{"t": "(1)", "p": "/us/md/cities/baltimore/code/31/9-3#(b)(1)", "et": "para", "sc": "Article 31, \u00a7 9-3(b)(1)", "x": "validated upon the expiration of 6 months from their date of issue; and"}, {"t": "(2)", "p": "/us/md/cities/baltimore/code/31/9-3#(b)(2)", "et": "para", "sc": "Article 31, \u00a7 9-3(b)(2)", "x": "renewed each year in the manner and form determined by the Department."}], "x": "Validation and renewal"}, {"t": "(c)", "p": "/us/md/cities/baltimore/code/31/9-3#(c)", "et": "para", "sc": "Article 31, \u00a7 9-3(c)", "x": "Notice when no longer needed."}, {"t": "(d)", "p": "/us/md/cities/baltimore/code/31/9-3#(d)", "et": "para", "sc": "Article 31, \u00a7 9-3(d)", "c": [{"t": "(1)", "p": "/us/md/cities/baltimore/code/31/9-3#(d)(1)", "et": "para", "sc": "Article 31, \u00a7 9-3(d)(1)", "x": "false statements are made in the application;"}, {"t": "(2)", "p": "/us/md/cities/baltimore/code/31/9-3#(d)(2)", "et": "para", "sc": "Article 31, \u00a7 9-3(d)(2)", "x": "the parking permit is misused;"}, {"t": "(3)", "p": "/us/md/cities/baltimore/code/31/9-3#(d)(3)", "et": "para", "sc": "Article 31, \u00a7 9-3(d)(3)", "x": "new parking regulations are imposed which prohibit parking at any time;"}, {"t": "(4)", "p": "/us/md/cities/baltimore/code/31/9-3#(d)(4)", "et": "para", "sc": "Article 31, \u00a7 9-3(d)(4)", "x": "the City Council rescinds an administrative regulation pursuant to \u00a7 2-6 of"}, {"t": "(5)", "p": "/us/md/cities/baltimore/code/31/9-3#(d)(5)", "et": "para", "sc": "Article 31, \u00a7 9-3(d)(5)", "x": "the disabled person dies, moves from the premises, or no longer needs the s"}], "x": "Revocation."}]}, {"t": "\u00a7 9-4. Forms, rules, and regulations; fees.", "p": "/us/md/cities/baltimore/code/31/9-4", "et": "section", "sc": " Article 31, \u00a7 9-4", "sp": "library|City of Baltimore, Md., Code|31|9|1|9-4", "c": [{"t": "(a)", "p": "/us/md/cities/baltimore/code/31/9-4#(a)", "et": "para", "sc": "Article 31, \u00a7 9-4(a)", "x": "Forms, rules, and regulations."}, {"t": "(b)", "p": "/us/md/cities/baltimore/code/31/9-4#(b)", "et": "para", "sc": "Article 31, \u00a7 9-4(b)", "c": [{"t": "(1)", "p": "/us/md/cities/baltimore/code/31/9-4#(b)(1)", "et": "para", "sc": "Article 31, \u00a7 9-4(b)(1)", "x": "The Director may set and impose reasonable application and annual permit fe"}, {"t": "(2)", "p": "/us/md/cities/baltimore/code/31/9-4#(b)(2)", "et": "para", "sc": "Article 31, \u00a7 9-4(b)(2)", "x": "The fees set under this subsection do not apply to and may not be imposed i"}], "x": "Fees."}]}, {"t": "9-5 to 9-10. {Reserved}", "p": "/us/md/cities/baltimore/code/31/9-5to9-10", "et": "section", "sc": " Article 31, 9-5 to 9-10", "sp": "library|City of Baltimore, Md., Code|31|9|1|9-5to9-10"}]}, {"t": "Part 2 Reserved Parking for Helpers", "p": "/us/md/cities/baltimore/code/31/9/2", "et": "container", "sc": " Article 31, Subtitle 9, Part 2", "sp": "library|City of Baltimore, Md., Code|31|9|2", "c": [{"t": "\u00a7 9-11. \"Disabled person\" defined.", "p": "/us/md/cities/baltimore/code/31/9-11", "et": "section", "sc": " Article 31, \u00a7 9-11", "sp": "library|City of Baltimore, Md., Code|31|9|2|9-11"}, {"t": "\u00a7 9-12. Criteria and procedure for obtaining.", "p": "/us/md/cities/baltimore/code/31/9-12", "et": "section", "sc": " Article 31, \u00a7 9-12", "sp": "library|City of Baltimore, Md., Code|31|9|2|9-12", "c": [{"t": "(a)", "p": "/us/md/cities/baltimore/code/31/9-12#(a)", "et": "para", "sc": "Article 31, \u00a7 9-12(a)", "x": "In general."}, {"t": "(b)", "p": "/us/md/cities/baltimore/code/31/9-12#(b)", "et": "para", "sc": "Article 31, \u00a7 9-12(b)", "c": [{"t": "(1)", "p": "/us/md/cities/baltimore/code/31/9-12#(b)(1)", "et": "para", "sc": "Article 31, \u00a7 9-12(b)(1)", "x": "The application shall be made jointly by the disabled person and the disabl"}, {"t": "(2)", "p": "/us/md/cities/baltimore/code/31/9-12#(b)(2)", "et": "para", "sc": "Article 31, \u00a7 9-12(b)(2)", "c": [{"t": "(i)", "p": "/us/md/cities/baltimore/code/31/9-12#(b)(2)(i)", "et": "para", "sc": "Article 31, \u00a7 9-12(b)(2)(i)", "x": "a physician's statement, dated within the previous 6 months, describing the"}, {"t": "(ii)", "p": "/us/md/cities/baltimore/code/31/9-12#(b)(2)(ii)", "et": "para", "sc": "Article 31, \u00a7 9-12(b)(2)(ii)", "x": "signed statements approving the designation of reserved parking for the app"}], "x": "The application shall be in the form that the Director requires and shall b"}, {"t": "(3)", "p": "/us/md/cities/baltimore/code/31/9-12#(b)(3)", "et": "para", "sc": "Article 31, \u00a7 9-12(b)(3)", "x": "The Director may waive the requirements of paragraph (2)(ii) of this subsec"}], "x": "Application."}, {"t": "(c)", "p": "/us/md/cities/baltimore/code/31/9-12#(c)", "et": "para", "sc": "Article 31, \u00a7 9-12(c)", "c": [{"t": "(1)", "p": "/us/md/cities/baltimore/code/31/9-12#(c)(1)", "et": "para", "sc": "Article 31, \u00a7 9-12(c)(1)", "x": "suitable off-street parking, such as a driveway, garage, or parking pad, is"}, {"t": "(2)", "p": "/us/md/cities/baltimore/code/31/9-12#(c)(2)", "et": "para", "sc": "Article 31, \u00a7 9-12(c)(2)", "x": "suitable parking space not restricted by other parking regulations is avail"}, {"t": "(3)", "p": "/us/md/cities/baltimore/code/31/9-12#(c)(3)", "et": "para", "sc": "Article 31, \u00a7 9-12(c)(3)", "x": "the disabled person meets the criteria for a reserved parking space."}], "x": "Review."}]}, {"t": "\u00a7 9-13. Assignment of space; restrictions.", "p": "/us/md/cities/baltimore/code/31/9-13", "et": "section", "sc": " Article 31, \u00a7 9-13", "sp": "library|City of Baltimore, Md., Code|31|9|2|9-13", "c": [{"t": "(a)", "p": "/us/md/cities/baltimore/code/31/9-13#(a)", "et": "para", "sc": "Article 31, \u00a7 9-13(a)", "x": "Assignment."}, {"t": "(b)", "p": "/us/md/cities/baltimore/code/31/9-13#(b)", "et": "para", "sc": "Article 31, \u00a7 9-13(b)", "c": [{"t": "(1)", "p": "/us/md/cities/baltimore/code/31/9-13#(b)(1)", "et": "para", "sc": "Article 31, \u00a7 9-13(b)(1)", "x": "The Director may specify the days, times, location, and other restrictions "}, {"t": "(2)", "p": "/us/md/cities/baltimore/code/31/9-13#(b)(2)", "et": "para", "sc": "Article 31, \u00a7 9-13(b)(2)", "x": "Any reserved parking space may be designated by the Director for use by mor"}], "x": "Restrictions."}]}, {"t": "\u00a7 9-14. Annual permit.", "p": "/us/md/cities/baltimore/code/31/9-14", "et": "section", "sc": " Article 31, \u00a7 9-14", "sp": "library|City of Baltimore, Md., Code|31|9|2|9-14", "c": [{"t": "(a)", "p": "/us/md/cities/baltimore/code/31/9-14#(a)", "et": "para", "sc": "Article 31, \u00a7 9-14(a)", "x": "Issuance."}, {"t": "(b)", "p": "/us/md/cities/baltimore/code/31/9-14#(b)", "et": "para", "sc": "Article 31, \u00a7 9-14(b)", "x": "Renewal."}]}, {"t": "\u00a7 9-15. Forms, rules, and regulations; fees.", "p": "/us/md/cities/baltimore/code/31/9-15", "et": "section", "sc": " Article 31, \u00a7 9-15", "sp": "library|City of Baltimore, Md., Code|31|9|2|9-15", "c": [{"t": "(a)", "p": "/us/md/cities/baltimore/code/31/9-15#(a)", "et": "para", "sc": "Article 31, \u00a7 9-15(a)", "x": "Forms, rules, and regulations."}, {"t": "(b)", "p": "/us/md/cities/baltimore/code/31/9-15#(b)", "et": "para", "sc": "Article 31, \u00a7 9-15(b)", "c": [{"t": "(1)", "p": "/us/md/cities/baltimore/code/31/9-15#(b)(1)", "et": "para", "sc": "Article 31, \u00a7 9-15(b)(1)", "x": "The Director may set and impose reasonable application and annual permit fe"}, {"t": "(2)", "p": "/us/md/cities/baltimore/code/31/9-15#(b)(2)", "et": "para", "sc": "Article 31, \u00a7 9-15(b)(2)", "x": "The fees set under this subsection do not apply to and may not be imposed i"}], "x": "Fees."}]}, {"t": "9-16 to 9-20. {Reserved}", "p": "/us/md/cities/baltimore/code/31/9-16to9-20", "et": "section", "sc": " Article 31, 9-16 to 9-20", "sp": "library|City of Baltimore, Md., Code|31|9|2|9-16to9-20"}]}, {"t": "Part 3 Towing Contracts for Parking Facilities", "p": "/us/md/cities/baltimore/code/31/9/3", "et": "container", "sc": " Article 31, Subtitle 9, Part 3", "sp": "library|City of Baltimore, Md., Code|31|9|3", "c": [{"t": "\u00a7 9-21. Contracts required.", "p": "/us/md/cities/baltimore/code/31/9-21", "et": "section", "sc": " Article 31, \u00a7 9-21", "sp": "library|City of Baltimore, Md., Code|31|9|3|9-21", "c": [{"t": "(1)", "p": "/us/md/cities/baltimore/code/31/9-21#(1)", "et": "para", "sc": "Article 31, \u00a7 9-21(1)", "x": "the owner has a contract for towing service to remove from the designated s"}, {"t": "(2)", "p": "/us/md/cities/baltimore/code/31/9-21#(2)", "et": "para", "sc": "Article 31, \u00a7 9-21(2)", "x": "the contract is effective for the period of certification."}]}]}]}