{"t": "Subtitle 12 Commercial Parking Facilities", "p": "/us/md/cities/baltimore/code/15/12", "et": "container", "dj": "/us/md/cities/baltimore/code/index.json", "fh": "/us/md/cities/baltimore/code/15/12/index.full.html", "sc": " Article 15, Subtitle 12", "sp": "library|City of Baltimore, Md., Code|15|12", "c": [{"t": "\u00a7 12-1. Definitions.", "p": "/us/md/cities/baltimore/code/15/12-1", "et": "section", "sc": " Article 15, \u00a7 12-1", "sp": "library|City of Baltimore, Md., Code|15|12|12-1", "c": [{"t": "(a)", "p": "/us/md/cities/baltimore/code/15/12-1#(a)", "et": "para", "sc": "Article 15, \u00a7 12-1(a)", "x": "In general."}, {"t": "(b)", "p": "/us/md/cities/baltimore/code/15/12-1#(b)", "et": "para", "sc": "Article 15, \u00a7 12-1(b)", "c": [{"t": "(1)", "p": "/us/md/cities/baltimore/code/15/12-1#(b)(1)", "et": "para", "sc": "Article 15, \u00a7 12-1(b)(1)", "x": "garage, structure, or part of a structure for the parking, storage, housing"}, {"t": "(2)", "p": "/us/md/cities/baltimore/code/15/12-1#(b)(2)", "et": "para", "sc": "Article 15, \u00a7 12-1(b)(2)", "x": "parking lot or outdoor area or space for the parking, storage, housing, or "}], "x": "Commercial parking facility."}, {"t": "(c)", "p": "/us/md/cities/baltimore/code/15/12-1#(c)", "et": "para", "sc": "Article 15, \u00a7 12-1(c)", "c": [{"t": "(1)", "p": "/us/md/cities/baltimore/code/15/12-1#(c)(1)", "et": "para", "sc": "Article 15, \u00a7 12-1(c)(1)", "x": "In general."}, {"t": "(2)", "p": "/us/md/cities/baltimore/code/15/12-1#(c)(2)", "et": "para", "sc": "Article 15, \u00a7 12-1(c)(2)", "x": "Inclusion of governmental entities."}], "x": "Person."}]}, {"t": "\u00a7 12-2. Subtitle inapplicable to special-event parking.", "p": "/us/md/cities/baltimore/code/15/12-2", "et": "section", "sc": " Article 15, \u00a7 12-2", "sp": "library|City of Baltimore, Md., Code|15|12|12-2"}, {"t": "12-3. {Reserved}", "p": "/us/md/cities/baltimore/code/15/12-3", "et": "section", "sc": " Article 15, 12-3", "sp": "library|City of Baltimore, Md., Code|15|12|12-3"}, {"t": "\u00a7 12-4. License required; fee.", "p": "/us/md/cities/baltimore/code/15/12-4", "et": "section", "sc": " Article 15, \u00a7 12-4", "sp": "library|City of Baltimore, Md., Code|15|12|12-4", "c": [{"t": "(a)", "p": "/us/md/cities/baltimore/code/15/12-4#(a)", "et": "para", "sc": "Article 15, \u00a7 12-4(a)", "c": [{"t": "(1)", "p": "/us/md/cities/baltimore/code/15/12-4#(a)(1)", "et": "para", "sc": "Article 15, \u00a7 12-4(a)(1)", "x": "No person may operate a commercial parking facility in the City of Baltimor"}, {"t": "(2)", "p": "/us/md/cities/baltimore/code/15/12-4#(a)(2)", "et": "para", "sc": "Article 15, \u00a7 12-4(a)(2)", "x": "The term of a license is from May 1 of each year through April 30 of the ne"}], "x": "In general."}, {"t": "(b)", "p": "/us/md/cities/baltimore/code/15/12-4#(b)", "et": "para", "sc": "Article 15, \u00a7 12-4(b)", "c": [{"t": "(1)", "p": "/us/md/cities/baltimore/code/15/12-4#(b)(1)", "et": "para", "sc": "Article 15, \u00a7 12-4(b)(1)", "x": "The annual fee for a commercial parking facility license is $5.10 for every"}, {"t": "(2)", "p": "/us/md/cities/baltimore/code/15/12-4#(b)(2)", "et": "para", "sc": "Article 15, \u00a7 12-4(b)(2)", "x": "For a license issued after July 31 and before November 1, the fee is 75% of"}, {"t": "(3)", "p": "/us/md/cities/baltimore/code/15/12-4#(b)(3)", "et": "para", "sc": "Article 15, \u00a7 12-4(b)(3)", "x": "For a license issued after October 31 and before February 1, the fee is 50%"}, {"t": "(4)", "p": "/us/md/cities/baltimore/code/15/12-4#(b)(4)", "et": "para", "sc": "Article 15, \u00a7 12-4(b)(4)", "x": "For a license issued after January 31, the fee is 25% of that prescribed fo"}], "x": "Fee."}, {"t": "(c)", "p": "/us/md/cities/baltimore/code/15/12-4#(c)", "et": "para", "sc": "Article 15, \u00a7 12-4(c)", "c": [{"t": "(1)", "p": "/us/md/cities/baltimore/code/15/12-4#(c)(1)", "et": "para", "sc": "Article 15, \u00a7 12-4(c)(1)", "x": "Any person desiring to operate a commercial parking facility for an aggrega"}, {"t": "(2)", "p": "/us/md/cities/baltimore/code/15/12-4#(c)(2)", "et": "para", "sc": "Article 15, \u00a7 12-4(c)(2)", "x": "The fee for a partial-year license is 1/12 of the annual license fee for ea"}], "x": "Partial-year license."}, {"t": "(d)", "p": "/us/md/cities/baltimore/code/15/12-4#(d)", "et": "para", "sc": "Article 15, \u00a7 12-4(d)", "x": "Online licensee list."}]}, {"t": "\u00a7 12-5. Transfer of licenses.", "p": "/us/md/cities/baltimore/code/15/12-5", "et": "section", "sc": " Article 15, \u00a7 12-5", "sp": "library|City of Baltimore, Md., Code|15|12|12-5"}, {"t": "\u00a7 12-6. Tax arrearage bars renewal or transfer.", "p": "/us/md/cities/baltimore/code/15/12-6", "et": "section", "sc": " Article 15, \u00a7 12-6", "sp": "library|City of Baltimore, Md., Code|15|12|12-6"}, {"t": "\u00a7 12-7. Refund on acquisition, etc., by City.", "p": "/us/md/cities/baltimore/code/15/12-7", "et": "section", "sc": " Article 15, \u00a7 12-7", "sp": "library|City of Baltimore, Md., Code|15|12|12-7"}, {"t": "\u00a7 12-8. Rules and regulations.", "p": "/us/md/cities/baltimore/code/15/12-8", "et": "section", "sc": " Article 15, \u00a7 12-8", "sp": "library|City of Baltimore, Md., Code|15|12|12-8"}, {"t": "\u00a7 12-9. Cars left in street.", "p": "/us/md/cities/baltimore/code/15/12-9", "et": "section", "sc": " Article 15, \u00a7 12-9", "sp": "library|City of Baltimore, Md., Code|15|12|12-9", "c": [{"t": "(a)", "p": "/us/md/cities/baltimore/code/15/12-9#(a)", "et": "para", "sc": "Article 15, \u00a7 12-9(a)", "x": "Prohibited conduct."}, {"t": "(b)", "p": "/us/md/cities/baltimore/code/15/12-9#(b)", "et": "para", "sc": "Article 15, \u00a7 12-9(b)", "c": [{"t": "(1)", "p": "/us/md/cities/baltimore/code/15/12-9#(b)(1)", "et": "para", "sc": "Article 15, \u00a7 12-9(b)(1)", "x": "Subsection (a) of this section does not apply to the parking or placement o"}, {"t": "(2)", "p": "/us/md/cities/baltimore/code/15/12-9#(b)(2)", "et": "para", "sc": "Article 15, \u00a7 12-9(b)(2)", "x": "This exception does not apply between 7 a.m. and 10 a.m. or between 4 p.m. "}], "x": "Exception."}]}, {"t": "\u00a7 12-10. Proof-of-payment required.", "p": "/us/md/cities/baltimore/code/15/12-10", "et": "section", "sc": " Article 15, \u00a7 12-10", "sp": "library|City of Baltimore, Md., Code|15|12|12-10", "c": [{"t": "(a)", "p": "/us/md/cities/baltimore/code/15/12-10#(a)", "et": "para", "sc": "Article 15, \u00a7 12-10(a)", "x": "In general."}, {"t": "(b)", "p": "/us/md/cities/baltimore/code/15/12-10#(b)", "et": "para", "sc": "Article 15, \u00a7 12-10(b)", "x": "Form."}]}, {"t": "\u00a7 12-11. Removal of vehicles.", "p": "/us/md/cities/baltimore/code/15/12-11", "et": "section", "sc": " Article 15, \u00a7 12-11", "sp": "library|City of Baltimore, Md., Code|15|12|12-11"}, {"t": "12-12. {Reserved}", "p": "/us/md/cities/baltimore/code/15/12-12", "et": "section", "sc": " Article 15, 12-12", "sp": "library|City of Baltimore, Md., Code|15|12|12-12"}, {"t": "\u00a7 12-13. License revocation.", "p": "/us/md/cities/baltimore/code/15/12-13", "et": "section", "sc": " Article 15, \u00a7 12-13", "sp": "library|City of Baltimore, Md., Code|15|12|12-13", "c": [{"t": "(a)", "p": "/us/md/cities/baltimore/code/15/12-13#(a)", "et": "para", "sc": "Article 15, \u00a7 12-13(a)", "x": "In general."}, {"t": "(b)", "p": "/us/md/cities/baltimore/code/15/12-13#(b)", "et": "para", "sc": "Article 15, \u00a7 12-13(b)", "x": "Form and effect of revocation."}, {"t": "(c)", "p": "/us/md/cities/baltimore/code/15/12-13#(c)", "et": "para", "sc": "Article 15, \u00a7 12-13(c)", "c": [{"t": "(1)", "p": "/us/md/cities/baltimore/code/15/12-13#(c)(1)", "et": "para", "sc": "Article 15, \u00a7 12-13(c)(1)", "x": "A license holder aggrieved by a decision if the Department of Finance may a"}, {"t": "(2)", "p": "/us/md/cities/baltimore/code/15/12-13#(c)(2)", "et": "para", "sc": "Article 15, \u00a7 12-13(c)(2)", "x": "The Director of Finance must issue a written decision within 30 days of rec"}], "x": "Administrative appeals."}]}, {"t": "\u00a7 12-14. Enforcement by citation.", "p": "/us/md/cities/baltimore/code/15/12-14", "et": "section", "sc": " Article 15, \u00a7 12-14", "sp": "library|City of Baltimore, Md., Code|15|12|12-14", "c": [{"t": "(a)", "p": "/us/md/cities/baltimore/code/15/12-14#(a)", "et": "para", "sc": "Article 15, \u00a7 12-14(a)", "x": "In general."}, {"t": "(b)", "p": "/us/md/cities/baltimore/code/15/12-14#(b)", "et": "para", "sc": "Article 15, \u00a7 12-14(b)", "x": "Process not exclusive."}, {"t": "(c)", "p": "/us/md/cities/baltimore/code/15/12-14#(c)", "et": "para", "sc": "Article 15, \u00a7 12-14(c)", "x": "Each day a separate offense."}, {"t": "(d)", "p": "/us/md/cities/baltimore/code/15/12-14#(d)", "et": "para", "sc": "Article 15, \u00a7 12-14(d)", "x": "Each vehicle towed a separate offense."}]}, {"t": "\u00a7 12-15. Criminal penalties.", "p": "/us/md/cities/baltimore/code/15/12-15", "et": "section", "sc": " Article 15, \u00a7 12-15", "sp": "library|City of Baltimore, Md., Code|15|12|12-15", "c": [{"t": "(a)", "p": "/us/md/cities/baltimore/code/15/12-15#(a)", "et": "para", "sc": "Article 15, \u00a7 12-15(a)", "x": "In general."}, {"t": "(b)", "p": "/us/md/cities/baltimore/code/15/12-15#(b)", "et": "para", "sc": "Article 15, \u00a7 12-15(b)", "x": "Each day a separate offense."}, {"t": "(c)", "p": "/us/md/cities/baltimore/code/15/12-15#(c)", "et": "para", "sc": "Article 15, \u00a7 12-15(c)", "x": "Each vehicle towed a separate offense."}]}]}